{
  "generator-jhipster": {
    "applicationType": "monolith",
    "gitCompany": "",
    "baseName": "jhipsterSampleApplication",
    "packageName": "com.mycompany.myapp",
    "packageFolder": "com/mycompany/myapp",
    "serverPort": 8080,
    "serviceDiscoveryType": false,
    "authenticationType": "jwt",
    "uaaBaseName": "../uaa",
    "cacheProvider": "ehcache",
    "enableHibernateCache": true,
    "websocket": false,
    "databaseType": "sql",
    "devDatabaseType": "h2Disk",
    "prodDatabaseType": "mysql",
    "searchEngine": false,
    "enableSwaggerCodegen": false,
    "messageBroker": "kafka",
    "buildTool": "maven",
    "useSass": true,
    "clientPackageManager": "npm",
    "testFrameworks": [],
    "enableTranslation": true,
    "nativeLanguage": "en",
    "languages": ["en"],
    "clientFramework": "angularX",
    "jhiPrefix": "jhi",
    "jhipsterVersion": "6.8.0",
    "jwtSecretKey": "ZDg4ODY4OGMwZjE0NTFlYjA4MmY2NzM5ZWNiNTQwNTgyYTRhNWU3NDczZmY4MjAwZGYxODcwYzczMzY4NDRlYTFjNGI5NzA5M2UyYThiMDRjZWQ3YWU3Y2I0MTcyYmQyZTlmZWI0YTE5MTM4ZmIwM2JiMDU2NTU3YmM2YjA3ZDQ=",
    "embeddableLaunchScript": false,
    "clientTheme": "none",
    "creationTimestamp": 1583811622607,
    "entitySuffix": "",
    "dtoSuffix": "DTO",
    "otherModules": [],
    "blueprints": []
  },
  "git-provider": "GitHub",
  "git-company": "tharathorn-inp",
  "repository-name": "jhipster-sample-application"
}
